LASED/AtomicState.py
LASED/__init__.py
LASED/angular_shape.py
LASED/constants.py
LASED/decay_constant.py
LASED/density_matrix.py
LASED/detuning.py
LASED/examplefunc.py
LASED/generate_sub_states.py
LASED/half_rabi_freq.py
LASED/index.py
LASED/laser_atom_system.py
LASED/matrix_methods.py
LASED/rotation.py
LASED/save_to_csv.py
LASED/state.py
LASED/symbolic_print.py
LASED/time_evolution.py
LASED/time_evolution_matrix.py
LASED-1.0.1.dist-info/METADATA
LASED-1.0.1.dist-info/WHEEL
LASED-1.0.1.dist-info/top_level.txt
LASED-1.0.1.dist-info/RECORD
