Metadata-Version: 2.1
Name: LASED
Version: 1.0.1
Summary: LASED
Home-page: UNKNOWN
Author: Manish Patel
Author-email: <mvpmanish@gmail.com>
License: UNKNOWN
Keywords: python,laser-atom,simulation,quantum,quantum electrodynamics,physics
Platform: UNKNOWN
Classifier: Development Status :: 5 - Production/Stable
Classifier: Intended Audience :: Science/Research
Classifier: Programming Language :: Python :: 2
Classifier: Programming Language :: Python :: 3
Classifier: Operating System :: OS Independent
Classifier: Natural Language :: English
Classifier: Topic :: Scientific/Engineering :: Physics
Requires-Dist: numpy (>=1.20)
Requires-Dist: scipy (>=1.6.0)
Requires-Dist: sympy (>=1.8)
